odoo/addons/account_tax_change/README.rst
odoo/addons/account_tax_change/__init__.py
odoo/addons/account_tax_change/__manifest__.py
odoo/addons/account_tax_change/i18n/account_tax_change.pot
odoo/addons/account_tax_change/i18n/es.po
odoo/addons/account_tax_change/i18n/it.po
odoo/addons/account_tax_change/models/__init__.py
odoo/addons/account_tax_change/models/account_tax_change.py
odoo/addons/account_tax_change/readme/CONFIGURE.rst
odoo/addons/account_tax_change/readme/CONTRIBUTORS.rst
odoo/addons/account_tax_change/readme/DESCRIPTION.rst
odoo/addons/account_tax_change/readme/USAGE.rst
odoo/addons/account_tax_change/security/ir.model.access.csv
odoo/addons/account_tax_change/static/description/account_tax_change.png
odoo/addons/account_tax_change/static/description/apply_tax_changes_form.png
odoo/addons/account_tax_change/static/description/apply_tax_changes_menu.png
odoo/addons/account_tax_change/static/description/icon.png
odoo/addons/account_tax_change/static/description/index.html
odoo/addons/account_tax_change/tests/__init__.py
odoo/addons/account_tax_change/tests/common.py
odoo/addons/account_tax_change/tests/test_account_tax_change.py
odoo/addons/account_tax_change/views/account_tax_change.xml
odoo/addons/account_tax_change/wizards/__init__.py
odoo/addons/account_tax_change/wizards/account_move_apply_tax_change.py
odoo/addons/account_tax_change/wizards/account_move_apply_tax_change.xml
odoo_addon_account_tax_change-16.0.1.0.3.1.dist-info/METADATA
odoo_addon_account_tax_change-16.0.1.0.3.1.dist-info/WHEEL
odoo_addon_account_tax_change-16.0.1.0.3.1.dist-info/top_level.txt
odoo_addon_account_tax_change-16.0.1.0.3.1.dist-info/RECORD
